mtc/__init__.py
mtc/adb.py
mtc_adb-0.0.3.dist-info/METADATA
mtc_adb-0.0.3.dist-info/WHEEL
mtc_adb-0.0.3.dist-info/top_level.txt
mtc_adb-0.0.3.dist-info/RECORD
