Metadata-Version: 2.1
Name: mtc-adb
Version: 0.0.3
Summary: 触控-adb
Author: KateTsengK
Author-email: cu2171505467@gmail.com
License: MIT
Keywords: Auto Script Testing
Requires-Python: >=3
Requires-Dist: mtc-base
Requires-Dist: adbutils
